{
    "bitcoin": {
        "symbol": "BTC",
        "hour": 0.2,
        "day": 1.08,
        "week": 7.44,
        "volume_std": 31890438874.453884,
        "volume_mean": 36733513891.55691,
        "last_24hour_volume": 32290927469.95516,
        "upper_std": -0.14
    },
    "ethereum": {
        "symbol": "ETH",
        "hour": 1.17,
        "day": 8.72,
        "week": 46.23,
        "volume_std": 12760123514.726492,
        "volume_mean": 19686433190.09976,
        "last_24hour_volume": 36889601657.66291,
        "upper_std": 1.35
    },
    "ripple": {
        "symbol": "XRP",
        "hour": 0.77,
        "day": 3.63,
        "week": 19.85,
        "volume_std": 2765692409.254862,
        "volume_mean": 4476646864.059627,
        "last_24hour_volume": 5262128491.173051,
        "upper_std": 0.28
    },
    "tether": {
        "symbol": "USDT",
        "hour": 0.0,
        "day": 0.0,
        "week": 0.01
    },
    "binancecoin": {
        "symbol": "BNB",
        "hour": 0.4,
        "day": 2.32,
        "week": 9.98
    },
    "solana": {
        "symbol": "SOL",
        "hour": 0.77,
        "day": 6.84,
        "week": 24.4
    },
    "usd-coin": {
        "symbol": "USDC",
        "hour": -0.0,
        "day": 0.0,
        "week": 0.0
    },
    "dogecoin": {
        "symbol": "DOGE",
        "hour": 1.66,
        "day": 8.34,
        "week": 40.3
    },
    "cardano": {
        "symbol": "ADA",
        "hour": 1.24,
        "day": 4.51,
        "week": 21.38
    },
    "tron": {
        "symbol": "TRX",
        "hour": 0.27,
        "day": 3.83,
        "week": 11.93
    },
    "staked-ether": {
        "symbol": "STETH",
        "hour": 1.04,
        "day": 8.63,
        "week": 46.06
    },
    "sui": {
        "symbol": "SUI",
        "hour": 0.56,
        "day": 2.16,
        "week": 17.97
    },
    "wrapped-bitcoin": {
        "symbol": "WBTC",
        "hour": 0.1,
        "day": 0.79,
        "week": 7.46
    },
    "chainlink": {
        "symbol": "LINK",
        "hour": 1.07,
        "day": 5.86,
        "week": 24.54
    },
    "wrapped-steth": {
        "symbol": "WSTETH",
        "hour": 1.08,
        "day": 8.96,
        "week": 45.95
    },
    "avalanche-2": {
        "symbol": "AVAX",
        "hour": 1.59,
        "day": 9.34,
        "week": 32.66
    },
    "stellar": {
        "symbol": "XLM",
        "hour": 0.68,
        "day": 2.67,
        "week": 19.07
    },
    "shiba-inu": {
        "symbol": "SHIB",
        "hour": 1.21,
        "day": 7.22,
        "week": 27.19
    },
    "pi-network": {
        "symbol": "PI",
        "hour": 0.87,
        "day": 21.03,
        "week": 122.76
    },
    "hedera-hashgraph": {
        "symbol": "HBAR",
        "hour": 0.92,
        "day": 3.97,
        "week": 21.47
    },
    "hyperliquid": {
        "symbol": "HYPE",
        "hour": 0.91,
        "day": 6.93,
        "week": 24.02
    },
    "the-open-network": {
        "symbol": "TON",
        "hour": -0.47,
        "day": 4.21,
        "week": 13.2
    },
    "bitcoin-cash": {
        "symbol": "BCH",
        "hour": 0.19,
        "day": 2.73,
        "week": 8.45
    },
    "leo-token": {
        "symbol": "LEO",
        "hour": 0.07,
        "day": 2.21,
        "week": 0.71
    },
    "polkadot": {
        "symbol": "DOT",
        "hour": 0.86,
        "day": 5.59,
        "week": 31.88
    },
    "litecoin": {
        "symbol": "LTC",
        "hour": 1.08,
        "day": 1.86,
        "week": 12.7
    },
    "weth": {
        "symbol": "WETH",
        "hour": 1.22,
        "day": 8.55,
        "week": 45.98
    },
    "usds": {
        "symbol": "USDS",
        "hour": 0.02,
        "day": 0.01,
        "week": 0.01
    },
    "monero": {
        "symbol": "XMR",
        "hour": 0.67,
        "day": 3.46,
        "week": 22.82
    },
    "wrapped-eeth": {
        "symbol": "WEETH",
        "hour": 1.0,
        "day": 8.31,
        "week": 46.1
    },
    "pepe": {
        "symbol": "PEPE",
        "hour": 1.61,
        "day": 7.32,
        "week": 77.01
    },
    "bitget-token": {
        "symbol": "BGB",
        "hour": 1.03,
        "day": 3.43,
        "week": 12.54
    },
    "binance-bridged-usdt-bnb-smart-chain": {
        "symbol": "BSC-USD",
        "hour": 0.09,
        "day": 0.16,
        "week": 0.14
    },
    "ethena-usde": {
        "symbol": "USDE",
        "hour": -0.28,
        "day": -0.29,
        "week": -0.28
    },
    "coinbase-wrapped-btc": {
        "symbol": "CBBTC",
        "hour": 0.25,
        "day": 1.09,
        "week": 7.51
    },
    "whitebit": {
        "symbol": "WBT",
        "hour": 0.13,
        "day": -0.36,
        "week": 6.98
    },
    "uniswap": {
        "symbol": "UNI",
        "hour": 0.69,
        "day": 3.6,
        "week": 40.59
    },
    "bittensor": {
        "symbol": "TAO",
        "hour": 1.15,
        "day": 3.47,
        "week": 23.45
    },
    "near": {
        "symbol": "NEAR",
        "hour": 1.23,
        "day": 5.26,
        "week": 40.99
    },
    "aptos": {
        "symbol": "APT",
        "hour": 1.45,
        "day": 8.07,
        "week": 27.33
    },
    "dai": {
        "symbol": "DAI",
        "hour": 0.01,
        "day": -0.04,
        "week": 0.01
    },
    "aave": {
        "symbol": "AAVE",
        "hour": 1.09,
        "day": 7.47,
        "week": 33.16
    },
    "okb": {
        "symbol": "OKB",
        "hour": 0.21,
        "day": 1.53,
        "week": 7.68
    },
    "ondo-finance": {
        "symbol": "ONDO",
        "hour": 1.16,
        "day": 4.01,
        "week": 19.05
    },
    "kaspa": {
        "symbol": "KAS",
        "hour": 3.0,
        "day": 7.98,
        "week": 35.83
    },
    "internet-computer": {
        "symbol": "ICP",
        "hour": 1.84,
        "day": 7.26,
        "week": 29.02
    },
    "ethereum-classic": {
        "symbol": "ETC",
        "hour": 0.43,
        "day": 6.57,
        "week": 26.53
    },
    "crypto-com-chain": {
        "symbol": "CRO",
        "hour": 0.7,
        "day": 4.97,
        "week": 11.64
    },
    "blackrock-usd-institutional-digital-liquidity-fund": {
        "symbol": "BUIDL",
        "hour": 0.0,
        "day": 0.0,
        "week": 0.0
    },
    "tokenize-xchange": {
        "symbol": "TKX",
        "hour": -0.39,
        "day": 7.8,
        "week": 22.16
    },
    "render-token": {
        "symbol": "RENDER",
        "hour": 1.7,
        "day": 5.64,
        "week": 22.71
    },
    "vechain": {
        "symbol": "VET",
        "hour": 0.93,
        "day": 5.86,
        "week": 27.45
    },
    "official-trump": {
        "symbol": "TRUMP",
        "hour": 0.77,
        "day": 7.37,
        "week": 24.03
    },
    "mantle": {
        "symbol": "MNT",
        "hour": 0.36,
        "day": 2.2,
        "week": 13.05
    },
    "gatechain-token": {
        "symbol": "GT",
        "hour": 0.53,
        "day": 3.01,
        "week": 3.34
    },
    "ethena": {
        "symbol": "ENA",
        "hour": 0.97,
        "day": 16.3,
        "week": 60.32
    },
    "cosmos": {
        "symbol": "ATOM",
        "hour": 0.42,
        "day": 2.69,
        "week": 27.23
    },
    "susds": {
        "symbol": "SUSDS",
        "hour": 0.0,
        "day": 0.01,
        "week": 0.08
    },
    "polygon-ecosystem-token": {
        "symbol": "POL",
        "hour": 0.98,
        "day": 5.06,
        "week": 18.68
    },
    "fetch-ai": {
        "symbol": "FET",
        "hour": 1.04,
        "day": 8.64,
        "week": 25.89
    },
    "arbitrum": {
        "symbol": "ARB",
        "hour": 1.5,
        "day": 8.93,
        "week": 47.99
    },
    "filecoin": {
        "symbol": "FIL",
        "hour": 0.74,
        "day": 6.96,
        "week": 25.35,
        "volume_std": 72081480.55914734,
        "volume_mean": 147281644.66843966,
        "last_24hour_volume": 190875521.0214844,
        "upper_std": 0.6
    },
    "algorand": {
        "symbol": "ALGO",
        "hour": 1.13,
        "day": 7.1,
        "week": 24.61,
        "volume_std": 44994942.989594325,
        "volume_mean": 93493628.25334963,
        "last_24hour_volume": 104978149.28932947,
        "upper_std": 0.26
    },
    "usd1-wlfi": {
        "symbol": "USD1",
        "hour": 0.12,
        "day": -0.02,
        "week": 0.18,
        "volume_std": 31695371.55847938,
        "volume_mean": 39011914.93093501,
        "last_24hour_volume": 18405347.811903607,
        "upper_std": -0.65
    },
    "ethena-staked-usde": {
        "symbol": "SUSDE",
        "hour": 0.02,
        "day": 0.01,
        "week": 0.26,
        "volume_std": 13067022.350986028,
        "volume_mean": 15988844.024174035,
        "last_24hour_volume": 12992336.516627017,
        "upper_std": -0.23
    },
    "celestia": {
        "symbol": "TIA",
        "hour": 0.42,
        "day": 8.08,
        "week": 39.97,
        "volume_std": 65992859.72645833,
        "volume_mean": 106007177.65277342,
        "last_24hour_volume": 167622225.13579315,
        "upper_std": 0.93
    },
    "lombard-staked-btc": {
        "symbol": "LBTC",
        "hour": 1.08,
        "day": 0.67,
        "week": 7.09,
        "volume_std": 8283313.194952827,
        "volume_mean": 8830220.217374811,
        "last_24hour_volume": 34765764.862986065,
        "upper_std": 3.13
    },
    "worldcoin-wld": {
        "symbol": "WLD",
        "hour": 0.83,
        "day": 6.73,
        "week": 36.19
    },
    "sonic-3": {
        "symbol": "S",
        "hour": 0.71,
        "day": 5.98,
        "week": 16.78
    },
    "fasttoken": {
        "symbol": "FTN",
        "hour": -0.0,
        "day": 0.02,
        "week": 1.66
    },
    "bonk": {
        "symbol": "BONK",
        "hour": 1.54,
        "day": 12.41,
        "week": 41.88
    },
    "jupiter-exchange-solana": {
        "symbol": "JUP",
        "hour": 1.65,
        "day": 5.65,
        "week": 34.03
    },
    "jupiter-perpetuals-liquidity-provider-token": {
        "symbol": "JLP",
        "hour": 0.43,
        "day": 3.56,
        "week": 13.89
    },
    "binance-peg-weth": {
        "symbol": "WETH",
        "hour": 1.25,
        "day": 8.78,
        "week": 46.86
    },
    "maker": {
        "symbol": "MKR",
        "hour": 1.85,
        "day": 10.21,
        "week": 31.06
    },
    "blockstack": {
        "symbol": "STX",
        "hour": 0.62,
        "day": 4.01,
        "week": 20.53
    },
    "first-digital-usd": {
        "symbol": "FDUSD",
        "hour": -0.13,
        "day": -0.07,
        "week": -0.09
    },
    "kelp-dao-restaked-eth": {
        "symbol": "RSETH",
        "hour": 0.24,
        "day": 7.61,
        "week": 44.82
    },
    "binance-staked-sol": {
        "symbol": "BNSOL",
        "hour": 0.22,
        "day": 6.34,
        "week": 23.35
    },
    "optimism": {
        "symbol": "OP",
        "hour": 1.26,
        "day": 11.39,
        "week": 44.07
    },
    "quant-network": {
        "symbol": "QNT",
        "hour": 0.89,
        "day": 4.42,
        "week": 13.06
    },
    "kucoin-shares": {
        "symbol": "KCS",
        "hour": 0.1,
        "day": 0.23,
        "week": 5.67
    },
    "fartcoin": {
        "symbol": "FARTCOIN",
        "hour": 2.56,
        "day": 10.57,
        "week": 37.3
    },
    "story-2": {
        "symbol": "IP",
        "hour": -0.33,
        "day": 6.84,
        "week": 30.77
    },
    "immutable-x": {
        "symbol": "IMX",
        "hour": 0.94,
        "day": 9.4,
        "week": 41.08
    },
    "injective-protocol": {
        "symbol": "INJ",
        "hour": 2.51,
        "day": 5.2,
        "week": 48.81
    },
    "sei-network": {
        "symbol": "SEI",
        "hour": 0.78,
        "day": 2.14,
        "week": 31.45
    },
    "eos": {
        "symbol": "EOS",
        "hour": 0.97,
        "day": 2.17,
        "week": 26.58
    },
    "flare-networks": {
        "symbol": "FLR",
        "hour": 0.88,
        "day": 3.34,
        "week": 7.77
    },
    "virtual-protocol": {
        "symbol": "VIRTUAL",
        "hour": 0.5,
        "day": 4.39,
        "week": 38.1
    },
    "nexo": {
        "symbol": "NEXO",
        "hour": 0.38,
        "day": 2.6,
        "week": 3.84
    },
    "rocket-pool-eth": {
        "symbol": "RETH",
        "hour": 0.89,
        "day": 8.34,
        "week": 45.83
    },
    "the-graph": {
        "symbol": "GRT",
        "hour": 0.55,
        "day": 11.06,
        "week": 41.58
    },
    "xdce-crowd-sale": {
        "symbol": "XDC",
        "hour": 0.47,
        "day": 3.04,
        "week": 4.85
    },
    "dogwifcoin": {
        "symbol": "WIF",
        "hour": -0.09,
        "day": 1.46,
        "week": 97.46
    },
    "usdt0": {
        "symbol": "USDT0",
        "hour": 0.06,
        "day": -0.05,
        "week": 0.04
    },
    "floki": {
        "symbol": "FLOKI",
        "hour": 0.29,
        "day": 5.36,
        "week": 47.78
    },
    "solv-btc": {
        "symbol": "SOLVBTC",
        "hour": 0.51,
        "day": 1.06,
        "week": 7.5
    },
    "theta-token": {
        "symbol": "THETA",
        "hour": 0.48,
        "day": 7.83,
        "week": 49.5
    },
    "curve-dao-token": {
        "symbol": "CRV",
        "hour": 0.86,
        "day": 5.69,
        "week": 12.86
    },
    "time": "May 14 2025 05:18:43"
}