{
    "bitcoin": {
        "symbol": "BTC",
        "hour": 0.19,
        "day": 1.74,
        "week": 1.14,
        "volume_std": 4939778251.446951,
        "volume_mean": 11995366474.145142,
        "last_24hour_volume": 15416970416.19046,
        "upper_std": 0.69
    },
    "ethereum": {
        "symbol": "ETH",
        "hour": -0.0,
        "day": 1.53,
        "week": 0.02,
        "volume_std": 3475073461.918324,
        "volume_mean": 7303322595.017013,
        "last_24hour_volume": 7711158331.890718,
        "upper_std": 0.12
    },
    "tether": {
        "symbol": "USDT",
        "hour": -0.0,
        "day": 0.19,
        "week": -0.02,
        "volume_std": 13183133433.543434,
        "volume_mean": 18268423305.755173,
        "last_24hour_volume": 24834661011.1436,
        "upper_std": 0.5
    },
    "binancecoin": {
        "symbol": "BNB",
        "hour": 0.15,
        "day": 0.38,
        "week": -0.65,
        "volume_std": 313137801.7983931,
        "volume_mean": 606655383.9253165,
        "last_24hour_volume": 450198661.6316186,
        "upper_std": -0.5
    },
    "ripple": {
        "symbol": "XRP",
        "hour": 0.18,
        "day": 4.31,
        "week": -7.05,
        "volume_std": 1460917320.5808315,
        "volume_mean": 1392094113.227266,
        "last_24hour_volume": 1326695348.2204833,
        "upper_std": -0.04
    },
    "usd-coin": {
        "symbol": "USDC",
        "hour": 0.02,
        "day": 0.05,
        "week": -0.05,
        "volume_std": 2820804891.902034,
        "volume_mean": 3767131168.95358,
        "last_24hour_volume": 4049048425.570009,
        "upper_std": 0.1
    },
    "staked-ether": {
        "symbol": "STETH",
        "hour": 0.04,
        "day": 1.57,
        "week": 0.14,
        "volume_std": 19829670.045265913,
        "volume_mean": 18836016.159322128,
        "last_24hour_volume": 55534916.60944552,
        "upper_std": 1.85
    },
    "dogecoin": {
        "symbol": "DOGE",
        "hour": 0.18,
        "day": 2.41,
        "week": -1.97,
        "volume_std": 304232557.8985379,
        "volume_mean": 413448371.5779728,
        "last_24hour_volume": 393184469.6423903,
        "upper_std": -0.07
    },
    "cardano": {
        "symbol": "ADA",
        "hour": -0.19,
        "day": 1.93,
        "week": -3.15,
        "volume_std": 185251326.17341647,
        "volume_mean": 249316043.42275685,
        "last_24hour_volume": 245064263.4295267,
        "upper_std": -0.02
    },
    "solana": {
        "symbol": "SOL",
        "hour": -0.29,
        "day": 6.38,
        "week": 4.53,
        "volume_std": 332803883.8055743,
        "volume_mean": 438809751.1951202,
        "last_24hour_volume": 597990819.0568392,
        "upper_std": 0.48
    },
    "tron": {
        "symbol": "TRX",
        "hour": -0.13,
        "day": 0.48,
        "week": -1.35,
        "volume_std": 116430764.3609562,
        "volume_mean": 297667492.5224491,
        "last_24hour_volume": 189435177.27104905,
        "upper_std": -0.93
    },
    "matic-network": {
        "symbol": "MATIC",
        "hour": 0.09,
        "day": 2.73,
        "week": -0.39,
        "volume_std": 149943816.93323484,
        "volume_mean": 275045218.09003556,
        "last_24hour_volume": 275981476.12801737,
        "upper_std": 0.01
    },
    "polkadot": {
        "symbol": "DOT",
        "hour": -0.08,
        "day": 1.13,
        "week": -2.13,
        "volume_std": 39971798.10188732,
        "volume_mean": 120761437.07939188,
        "last_24hour_volume": 97796950.30246,
        "upper_std": -0.57
    },
    "litecoin": {
        "symbol": "LTC",
        "hour": -0.22,
        "day": 1.19,
        "week": -8.24
    },
    "shiba-inu": {
        "symbol": "SHIB",
        "hour": 0.49,
        "day": 10.74,
        "week": 19.31
    },
    "wrapped-bitcoin": {
        "symbol": "WBTC",
        "hour": 0.39,
        "day": 2.03,
        "week": 1.36
    },
    "uniswap": {
        "symbol": "UNI",
        "hour": -0.15,
        "day": 3.63,
        "week": -3.65
    },
    "bitcoin-cash": {
        "symbol": "BCH",
        "hour": -0.16,
        "day": -2.48,
        "week": -0.84
    },
    "the-open-network": {
        "symbol": "TON",
        "hour": 0.29,
        "day": 5.59,
        "week": 6.71
    },
    "avalanche-2": {
        "symbol": "AVAX",
        "hour": -0.08,
        "day": 1.1,
        "week": -0.83
    },
    "chainlink": {
        "symbol": "LINK",
        "hour": 0.59,
        "day": 4.21,
        "week": 0.58
    },
    "dai": {
        "symbol": "DAI",
        "hour": -0.09,
        "day": -0.02,
        "week": -0.02
    },
    "stellar": {
        "symbol": "XLM",
        "hour": -0.44,
        "day": 2.17,
        "week": -4.74
    },
    "leo-token": {
        "symbol": "LEO",
        "hour": -0.07,
        "day": 0.32,
        "week": 1.46
    },
    "binance-usd": {
        "symbol": "BUSD",
        "hour": 0.07,
        "day": 0.01,
        "week": -0.08
    },
    "true-usd": {
        "symbol": "TUSD",
        "hour": 0.11,
        "day": 0.0,
        "week": -0.09
    },
    "okb": {
        "symbol": "OKB",
        "hour": 0.07,
        "day": 5.04,
        "week": 13.28
    },
    "monero": {
        "symbol": "XMR",
        "hour": 0.23,
        "day": 0.3,
        "week": -0.87
    },
    "ethereum-classic": {
        "symbol": "ETC",
        "hour": 0.04,
        "day": 1.32,
        "week": -1.86
    },
    "cosmos": {
        "symbol": "ATOM",
        "hour": 0.05,
        "day": 0.05,
        "week": -3.65
    },
    "hedera-hashgraph": {
        "symbol": "HBAR",
        "hour": -0.04,
        "day": 4.06,
        "week": 21.2
    },
    "filecoin": {
        "symbol": "FIL",
        "hour": 0.07,
        "day": 1.41,
        "week": -2.14
    },
    "internet-computer": {
        "symbol": "ICP",
        "hour": -0.04,
        "day": 0.09,
        "week": -1.53
    },
    "lido-dao": {
        "symbol": "LDO",
        "hour": -0.28,
        "day": 1.61,
        "week": -0.49
    },
    "crypto-com-chain": {
        "symbol": "CRO",
        "hour": -0.09,
        "day": 0.57,
        "week": -2.36
    },
    "mantle": {
        "symbol": "MNT",
        "hour": -0.08,
        "day": -7.39,
        "week": -10.45
    },
    "arbitrum": {
        "symbol": "ARB",
        "hour": -0.2,
        "day": 2.58,
        "week": 1.71
    },
    "quant-network": {
        "symbol": "QNT",
        "hour": 0.24,
        "day": 0.36,
        "week": -3.49
    },
    "aptos": {
        "symbol": "APT",
        "hour": 0.01,
        "day": 1.03,
        "week": -3.42
    },
    "vechain": {
        "symbol": "VET",
        "hour": -0.24,
        "day": 1.03,
        "week": -4.89
    },
    "near": {
        "symbol": "NEAR",
        "hour": -0.22,
        "day": 0.52,
        "week": -2.97
    },
    "optimism": {
        "symbol": "OP",
        "hour": -0.59,
        "day": -1.29,
        "week": 1.03
    },
    "maker": {
        "symbol": "MKR",
        "hour": -0.15,
        "day": -0.76,
        "week": -7.72
    },
    "rocket-pool-eth": {
        "symbol": "RETH",
        "hour": -0.04,
        "day": 1.29,
        "week": 0.73
    },
    "the-graph": {
        "symbol": "GRT",
        "hour": 0.11,
        "day": 1.16,
        "week": -2.26
    },
    "aave": {
        "symbol": "AAVE",
        "hour": 0.16,
        "day": 2.53,
        "week": 6.64
    },
    "kaspa": {
        "symbol": "KAS",
        "hour": 0.67,
        "day": 0.06,
        "week": 13.49
    },
    "algorand": {
        "symbol": "ALGO",
        "hour": 0.49,
        "day": -2.78,
        "week": 4.6
    },
    "xdce-crowd-sale": {
        "symbol": "XDC",
        "hour": -1.61,
        "day": -7.22,
        "week": -4.9
    },
    "havven": {
        "symbol": "SNX",
        "hour": -0.08,
        "day": 5.17,
        "week": 2.97
    },
    "the-sandbox": {
        "symbol": "SAND",
        "hour": 0.04,
        "day": 0.57,
        "week": -3.23
    },
    "blockstack": {
        "symbol": "STX",
        "hour": 0.17,
        "day": 3.85,
        "week": -3.53
    },
    "frax": {
        "symbol": "FRAX",
        "hour": 0.01,
        "day": 0.09,
        "week": 0.09
    },
    "elrond-erd-2": {
        "symbol": "EGLD",
        "hour": 0.49,
        "day": -0.87,
        "week": -1.33
    },
    "eos": {
        "symbol": "EOS",
        "hour": -0.13,
        "day": 1.01,
        "week": -2.8
    },
    "whitebit": {
        "symbol": "WBT",
        "hour": -0.09,
        "day": 0.47,
        "week": 0.68
    },
    "immutable-x": {
        "symbol": "IMX",
        "hour": -0.33,
        "day": 1.42,
        "week": -5.96
    },
    "axie-infinity": {
        "symbol": "AXS",
        "hour": -0.11,
        "day": 0.82,
        "week": -2.4
    },
    "tezos": {
        "symbol": "XTZ",
        "hour": 0.46,
        "day": 1.16,
        "week": -5.31
    },
    "theta-token": {
        "symbol": "THETA",
        "hour": 0.88,
        "day": 3.09,
        "week": -2.57
    },
    "usdd": {
        "symbol": "USDD",
        "hour": 0.02,
        "day": 0.16,
        "week": -0.09
    },
    "flex-coin": {
        "symbol": "FLEX",
        "hour": -0.04,
        "day": 8.67,
        "week": 40.85
    },
    "bitcoin-cash-sv": {
        "symbol": "BSV",
        "hour": -0.03,
        "day": 0.01,
        "week": -4.63
    },
    "decentraland": {
        "symbol": "MANA",
        "hour": -0.06,
        "day": 1.5,
        "week": -2.45
    },
    "apecoin": {
        "symbol": "APE",
        "hour": -0.2,
        "day": 0.94,
        "week": 1.45
    },
    "fantom": {
        "symbol": "FTM",
        "hour": 0.03,
        "day": 2.29,
        "week": -2.9
    },
    "injective-protocol": {
        "symbol": "INJ",
        "hour": -0.64,
        "day": -1.27,
        "week": -1.2
    },
    "bitget-token": {
        "symbol": "BGB",
        "hour": -0.37,
        "day": 1.13,
        "week": 0.64,
        "volume_std": 3494403.0377640617,
        "volume_mean": 15764587.257797642,
        "last_24hour_volume": 13608231.289013615,
        "upper_std": -0.62
    },
    "render-token": {
        "symbol": "RNDR",
        "hour": 0.26,
        "day": 4.88,
        "week": -6.7,
        "volume_std": 54815634.65820113,
        "volume_mean": 64173872.18523437,
        "last_24hour_volume": 22120971.066109218,
        "upper_std": -0.77
    },
    "neo": {
        "symbol": "NEO",
        "hour": -0.14,
        "day": 0.99,
        "week": -3.21,
        "volume_std": 25355639.73517876,
        "volume_mean": 35725005.6201018,
        "last_24hour_volume": 20911872.405707862,
        "upper_std": -0.58
    },
    "gala": {
        "symbol": "GALA",
        "hour": 0.11,
        "day": 1.91,
        "week": 0.42,
        "volume_std": 167593039.06911448,
        "volume_mean": 174725276.40456325,
        "last_24hour_volume": 493215157.85881203,
        "upper_std": 1.9
    },
    "flow": {
        "symbol": "FLOW",
        "hour": -0.0,
        "day": 1.48,
        "week": -3.59,
        "volume_std": 46760442.88921943,
        "volume_mean": 27357061.536076408,
        "last_24hour_volume": 23157241.553131975,
        "upper_std": -0.09
    },
    "ecash": {
        "symbol": "XEC",
        "hour": -0.26,
        "day": -0.17,
        "week": -2.9,
        "volume_std": 99907525.20657218,
        "volume_mean": 29016115.17066055,
        "last_24hour_volume": 14031893.869354581,
        "upper_std": -0.15
    },
    "kava": {
        "symbol": "KAVA",
        "hour": 0.23,
        "day": 0.81,
        "week": -4.1,
        "volume_std": 30641068.452020854,
        "volume_mean": 26201727.37548751,
        "last_24hour_volume": 7793073.08269178,
        "upper_std": -0.6
    },
    "gatechain-token": {
        "symbol": "GT",
        "hour": -0.0,
        "day": 0.56,
        "week": -1.0,
        "volume_std": 307612.520509376,
        "volume_mean": 546807.4258442341,
        "last_24hour_volume": 537324.7603913137,
        "upper_std": -0.03
    },
    "kucoin-shares": {
        "symbol": "KCS",
        "hour": 0.04,
        "day": 0.32,
        "week": -0.96,
        "volume_std": 901687.3984919186,
        "volume_mean": 1458407.3290920623,
        "last_24hour_volume": 767201.803544061,
        "upper_std": -0.77
    },
    "radix": {
        "symbol": "XRD",
        "hour": -0.14,
        "day": -0.13,
        "week": -4.5,
        "volume_std": 1501939.8514701868,
        "volume_mean": 2822621.8614810505,
        "last_24hour_volume": 1495654.3868685379,
        "upper_std": -0.88
    },
    "chiliz": {
        "symbol": "CHZ",
        "hour": -0.12,
        "day": 1.14,
        "week": -1.4,
        "volume_std": 18505627.989356562,
        "volume_mean": 35147636.15012107,
        "last_24hour_volume": 30553364.931572065,
        "upper_std": -0.25
    },
    "pepe": {
        "symbol": "PEPE",
        "hour": 0.9,
        "day": 13.55,
        "week": 0.69,
        "volume_std": 149095973.86469483,
        "volume_mean": 167465129.16769817,
        "last_24hour_volume": 191066396.38981298,
        "upper_std": 0.16
    },
    "rollbit-coin": {
        "symbol": "RLB",
        "hour": 2.49,
        "day": 58.54,
        "week": 104.51,
        "volume_std": 6491289.757232094,
        "volume_mean": 4397294.14778537,
        "last_24hour_volume": 53241995.88064555,
        "upper_std": 7.52
    },
    "curve-dao-token": {
        "symbol": "CRV",
        "hour": 0.36,
        "day": 0.8,
        "week": 7.59,
        "volume_std": 62530335.61456421,
        "volume_mean": 58084038.17989133,
        "last_24hour_volume": 72664332.0577041,
        "upper_std": 0.23
    },
    "rocket-pool": {
        "symbol": "RPL",
        "hour": -0.66,
        "day": 2.45,
        "week": -11.88,
        "volume_std": 3312587.7691497416,
        "volume_mean": 5182119.285498133,
        "last_24hour_volume": 9926470.669465495,
        "upper_std": 1.43
    },
    "paxos-standard": {
        "symbol": "USDP",
        "hour": 0.03,
        "day": -0.04,
        "week": -0.13,
        "volume_std": 14352290.462319177,
        "volume_mean": 11316362.439165138,
        "last_24hour_volume": 6649403.305664853,
        "upper_std": -0.33
    },
    "klay-token": {
        "symbol": "KLAY",
        "hour": -0.14,
        "day": 0.68,
        "week": -1.44,
        "volume_std": 8162149.41004962,
        "volume_mean": 12639665.00811146,
        "last_24hour_volume": 3665484.5824702075,
        "upper_std": -1.1
    },
    "compound-ether": {
        "symbol": "CETH",
        "hour": -0.02,
        "day": 1.56,
        "week": 0.12
    },
    "iota": {
        "symbol": "MIOTA",
        "hour": -0.2,
        "day": 1.46,
        "week": -0.3
    },
    "pax-gold": {
        "symbol": "PAXG",
        "hour": -0.03,
        "day": -0.14,
        "week": -0.57
    },
    "tether-gold": {
        "symbol": "XAUT",
        "hour": -0.01,
        "day": 0.17,
        "week": -1.15
    },
    "frax-share": {
        "symbol": "FXS",
        "hour": -0.16,
        "day": 2.52,
        "week": 10.33
    },
    "tokenize-xchange": {
        "symbol": "TKX",
        "hour": 0.14,
        "day": 2.21,
        "week": -0.31
    },
    "frax-ether": {
        "symbol": "FRXETH",
        "hour": 0.02,
        "day": 1.57,
        "week": 0.14
    },
    "terra-luna": {
        "symbol": "LUNC",
        "hour": 0.02,
        "day": 0.82,
        "week": -3.15
    },
    "gmx": {
        "symbol": "GMX",
        "hour": 0.0,
        "day": 0.52,
        "week": -1.47
    },
    "bittorrent": {
        "symbol": "BTT",
        "hour": -0.04,
        "day": 0.19,
        "week": 0.07
    },
    "mina-protocol": {
        "symbol": "MINA",
        "hour": 0.39,
        "day": 1.86,
        "week": 4.53
    },
    "sui": {
        "symbol": "SUI",
        "hour": 0.09,
        "day": 2.35,
        "week": -5.24
    },
    "casper-network": {
        "symbol": "CSPR",
        "hour": -0.08,
        "day": -3.26,
        "week": 0.52
    },
    "huobi-token": {
        "symbol": "HT",
        "hour": 0.22,
        "day": 0.63,
        "week": -2.33
    },
    "compound-governance-token": {
        "symbol": "COMP",
        "hour": -0.63,
        "day": 2.06,
        "week": -12.61
    },
    "trust-wallet-token": {
        "symbol": "TWT",
        "hour": -0.06,
        "day": 0.34,
        "week": -3.18
    },
    "time": "Aug 09 2023 12:26:30"
}