{
    "bitcoin": {
        "symbol": "BTC",
        "hour": 0.61,
        "day": 3.48,
        "week": 14.18,
        "volume_std": 7712730888.718604,
        "volume_mean": 34766266376.89384,
        "last_24hour_volume": 51065773954.29807,
        "upper_std": 2.11
    },
    "ethereum": {
        "symbol": "ETH",
        "hour": 0.76,
        "day": 0.31,
        "week": 8.58,
        "volume_std": 6050885651.971066,
        "volume_mean": 23666121422.79165,
        "last_24hour_volume": 22219116995.924385,
        "upper_std": -0.24
    },
    "binancecoin": {
        "symbol": "BNB",
        "hour": 0.83,
        "day": 0.35,
        "week": 13.89,
        "volume_std": 664886318.8946958,
        "volume_mean": 1851994663.26106,
        "last_24hour_volume": 2641065171.1135597,
        "upper_std": 1.19
    },
    "cardano": {
        "symbol": "ADA",
        "hour": 0.55,
        "day": 2.24,
        "week": 0.09,
        "volume_std": 2073289512.4171474,
        "volume_mean": 3477589739.176158,
        "last_24hour_volume": 2719018769.719894,
        "upper_std": -0.37
    },
    "tether": {
        "symbol": "USDT",
        "hour": 0.47,
        "day": -0.59,
        "week": 0.18,
        "volume_std": 14497343071.010635,
        "volume_mean": 65850580264.172035,
        "last_24hour_volume": 81598878585.37888,
        "upper_std": 1.09
    },
    "ripple": {
        "symbol": "XRP",
        "hour": 0.95,
        "day": 0.46,
        "week": 7.79,
        "volume_std": 2014163618.2851572,
        "volume_mean": 4600429570.011527,
        "last_24hour_volume": 6476889301.740267,
        "upper_std": 0.93
    },
    "solana": {
        "symbol": "SOL",
        "hour": 0.38,
        "day": 5.28,
        "week": 0.3,
        "volume_std": 2699595793.2530184,
        "volume_mean": 2807309423.011775,
        "last_24hour_volume": 3746068171.2773514,
        "upper_std": 0.35
    },
    "polkadot": {
        "symbol": "DOT",
        "hour": 0.61,
        "day": 8.25,
        "week": 32.26,
        "volume_std": 930267114.3643351,
        "volume_mean": 1652309987.0719566,
        "last_24hour_volume": 3507961783.958079,
        "upper_std": 1.99
    },
    "usd-coin": {
        "symbol": "USDC",
        "hour": 0.25,
        "day": -0.82,
        "week": 0.19,
        "volume_std": 756472033.2692151,
        "volume_mean": 2631098760.8033304,
        "last_24hour_volume": 3372786952.25936,
        "upper_std": 0.98
    },
    "dogecoin": {
        "symbol": "DOGE",
        "hour": 0.67,
        "day": 2.23,
        "week": -1.33,
        "volume_std": 1334242783.105496,
        "volume_mean": 2169192542.4360175,
        "last_24hour_volume": 1913449279.3156998,
        "upper_std": -0.19
    },
    "terra-luna": {
        "symbol": "LUNA",
        "hour": 0.92,
        "day": -0.6,
        "week": -13.83,
        "volume_std": 694938127.6236349,
        "volume_mean": 1044011433.8615055,
        "last_24hour_volume": 794959056.5615085,
        "upper_std": -0.36
    },
    "uniswap": {
        "symbol": "UNI",
        "hour": 0.91,
        "day": -2.03,
        "week": 5.5,
        "volume_std": 232369606.50705698,
        "volume_mean": 499212853.34699047,
        "last_24hour_volume": 423815619.7942318,
        "upper_std": -0.32
    },
    "wrapped-bitcoin": {
        "symbol": "WBTC",
        "hour": 0.34,
        "day": 2.47,
        "week": 13.08,
        "volume_std": 125309279.19299781,
        "volume_mean": 384043362.574659,
        "last_24hour_volume": 714986192.6973598,
        "upper_std": 2.64
    },
    "litecoin": {
        "symbol": "LTC",
        "hour": 0.73,
        "day": 3.15,
        "week": 8.67,
        "volume_std": 1034068230.1733537,
        "volume_mean": 2580280555.6785226,
        "last_24hour_volume": 3202606016.9640074,
        "upper_std": 0.6
    },
    "binance-usd": {
        "symbol": "BUSD",
        "hour": 0.4,
        "day": -0.24,
        "week": 0.21,
        "volume_std": 1700051396.6812134,
        "volume_mean": 5210061825.155907,
        "last_24hour_volume": 8042122222.287023,
        "upper_std": 1.67
    },
    "shiba-inu": {
        "symbol": "SHIB",
        "hour": 0.47,
        "day": -6.78,
        "week": -7.86,
        "volume_std": 2860528139.9365373,
        "volume_mean": 1271448984.275805,
        "last_24hour_volume": 3501745684.010302,
        "upper_std": 0.78
    },
    "chainlink": {
        "symbol": "LINK",
        "hour": 0.85,
        "day": 1.5,
        "week": 4.16,
        "volume_std": 477405596.2202785,
        "volume_mean": 1253974453.6874702,
        "last_24hour_volume": 1165923100.6858044,
        "upper_std": -0.18
    },
    "avalanche-2": {
        "symbol": "AVAX",
        "hour": 0.91,
        "day": 0.91,
        "week": -6.01,
        "volume_std": 771872466.9410892,
        "volume_mean": 881347157.8496516,
        "last_24hour_volume": 528455112.961992,
        "upper_std": -0.46
    },
    "bitcoin-cash": {
        "symbol": "BCH",
        "hour": 0.75,
        "day": 3.9,
        "week": 6.62,
        "volume_std": 1897033739.0705965,
        "volume_mean": 5215089156.116215,
        "last_24hour_volume": 8717134378.008087,
        "upper_std": 1.85
    },
    "algorand": {
        "symbol": "ALGO",
        "hour": 0.88,
        "day": -1.98,
        "week": -6.99,
        "volume_std": 636082121.4344568,
        "volume_mean": 511267598.1567629,
        "last_24hour_volume": 301328483.7098035,
        "upper_std": -0.33
    },
    "matic-network": {
        "symbol": "MATIC",
        "hour": 0.49,
        "day": 19.16,
        "week": 13.08,
        "volume_std": 527514382.20251787,
        "volume_mean": 1011248652.8776339,
        "last_24hour_volume": 4323335915.453742,
        "upper_std": 6.28
    },
    "cosmos": {
        "symbol": "ATOM",
        "hour": 0.95,
        "day": -0.78,
        "week": -3.98,
        "volume_std": 684908181.3927083,
        "volume_mean": 873628691.2259221,
        "last_24hour_volume": 544094629.8099843,
        "upper_std": -0.48
    },
    "stellar": {
        "symbol": "XLM",
        "hour": -0.15,
        "day": 1.0,
        "week": 11.13,
        "volume_std": 297809972.5693566,
        "volume_mean": 674626734.845528,
        "last_24hour_volume": 885532828.6785141,
        "upper_std": 0.71
    },
    "vechain": {
        "symbol": "VET",
        "hour": 0.81,
        "day": 0.78,
        "week": 7.73,
        "volume_std": 291635068.4155947,
        "volume_mean": 704097872.4313914,
        "last_24hour_volume": 669948311.5599222,
        "upper_std": -0.12
    },
    "axie-infinity": {
        "symbol": "AXS",
        "hour": 0.88,
        "day": -10.3,
        "week": 0.58,
        "volume_std": 1235064702.484273,
        "volume_mean": 1253195305.9358377,
        "last_24hour_volume": 1014755780.4785637,
        "upper_std": -0.19
    },
    "filecoin": {
        "symbol": "FIL",
        "hour": 0.6,
        "day": -2.78,
        "week": -14.32,
        "volume_std": 736360620.999573,
        "volume_mean": 999327909.1225098,
        "last_24hour_volume": 915199320.1461244,
        "upper_std": -0.11
    },
    "internet-computer": {
        "symbol": "ICP",
        "hour": 1.54,
        "day": 2.27,
        "week": -10.8,
        "volume_std": 302556696.2374112,
        "volume_mean": 479130927.20977724,
        "last_24hour_volume": 427231930.33374506,
        "upper_std": -0.17
    },
    "tron": {
        "symbol": "TRX",
        "hour": 0.83,
        "day": 1.67,
        "week": 2.42,
        "volume_std": 613660600.6686499,
        "volume_mean": 1415840991.2928762,
        "last_24hour_volume": 1549854843.32845,
        "upper_std": 0.22
    },
    "ethereum-classic": {
        "symbol": "ETC",
        "hour": 0.89,
        "day": -1.0,
        "week": 1.96,
        "volume_std": 1215266303.8131695,
        "volume_mean": 4058290688.0598664,
        "last_24hour_volume": 3541596961.1410255,
        "upper_std": -0.43
    },
    "dai": {
        "symbol": "DAI",
        "hour": 0.75,
        "day": -0.27,
        "week": 0.36,
        "volume_std": 288167954.33842963,
        "volume_mean": 480348173.2203153,
        "last_24hour_volume": 1147450403.7347999,
        "upper_std": 2.31
    },
    "ftx-token": {
        "symbol": "FTT",
        "hour": 0.84,
        "day": 0.76,
        "week": 3.76,
        "volume_std": 638270451.7658539,
        "volume_mean": 531688439.69574815,
        "last_24hour_volume": 296481422.10053146,
        "upper_std": -0.37
    },
    "theta-token": {
        "symbol": "THETA",
        "hour": 0.93,
        "day": 3.55,
        "week": -1.91,
        "volume_std": 205938425.17112252,
        "volume_mean": 380495382.34386015,
        "last_24hour_volume": 285981493.1164832,
        "upper_std": -0.46
    },
    "compound-ether": {
        "symbol": "CETH",
        "hour": 0.76,
        "day": 0.59,
        "week": 8.19,
        "volume_std": 73089203.44719236,
        "volume_mean": 50971496.0626931,
        "last_24hour_volume": 12232471.567717286,
        "upper_std": -0.53
    },
    "tezos": {
        "symbol": "XTZ",
        "hour": 0.69,
        "day": -1.23,
        "week": -4.59,
        "volume_std": 482524086.3230271,
        "volume_mean": 506147723.2339218,
        "last_24hour_volume": 324390386.28434503,
        "upper_std": -0.38
    },
    "hedera-hashgraph": {
        "symbol": "HBAR",
        "hour": 0.59,
        "day": -2.68,
        "week": -0.21,
        "volume_std": 194602450.3495769,
        "volume_mean": 186211319.08229545,
        "last_24hour_volume": 145141838.72023156,
        "upper_std": -0.21
    },
    "staked-ether": {
        "symbol": "STETH",
        "hour": 1.04,
        "day": 0.44,
        "week": 8.31,
        "volume_std": 15398595.890377693,
        "volume_mean": 14456409.27206515,
        "last_24hour_volume": 6384830.999378143,
        "upper_std": -0.52
    },
    "fantom": {
        "symbol": "FTM",
        "hour": 1.2,
        "day": -4.58,
        "week": -14.39,
        "volume_std": 541165391.0927719,
        "volume_mean": 453402207.37068266,
        "last_24hour_volume": 490373699.56160533,
        "upper_std": 0.07
    },
    "monero": {
        "symbol": "XMR",
        "hour": 0.13,
        "day": 0.48,
        "week": -3.01,
        "volume_std": 57766323.95927991,
        "volume_mean": 237512009.20569134,
        "last_24hour_volume": 261400897.73247147,
        "upper_std": 0.41
    },
    "crypto-com-chain": {
        "symbol": "CRO",
        "hour": 0.72,
        "day": 0.08,
        "week": -0.11,
        "volume_std": 18233755.795554,
        "volume_mean": 50983790.55600022,
        "last_24hour_volume": 60949754.30753208,
        "upper_std": 0.55
    },
    "elrond-erd-2": {
        "symbol": "EGLD",
        "hour": 0.7,
        "day": -0.9,
        "week": -6.28,
        "volume_std": 140045814.72226948,
        "volume_mean": 161250784.33247194,
        "last_24hour_volume": 96763899.65367436,
        "upper_std": -0.46
    },
    "pancakeswap-token": {
        "symbol": "CAKE",
        "hour": 1.14,
        "day": -0.41,
        "week": 2.73,
        "volume_std": 87173927.06866656,
        "volume_mean": 241013832.2857154,
        "last_24hour_volume": 223928505.86551055,
        "upper_std": -0.2
    },
    "eos": {
        "symbol": "EOS",
        "hour": 0.58,
        "day": -0.54,
        "week": 0.51,
        "volume_std": 523410564.8266459,
        "volume_mean": 1537755687.0549798,
        "last_24hour_volume": 1356830876.4297936,
        "upper_std": -0.35
    },
    "okb": {
        "symbol": "OKB",
        "hour": 1.0,
        "day": 0.96,
        "week": -7.46,
        "volume_std": 196754117.40642336,
        "volume_mean": 411908390.1757419,
        "last_24hour_volume": 275441237.33201075,
        "upper_std": -0.69
    },
    "near": {
        "symbol": "NEAR",
        "hour": -0.06,
        "day": 1.59,
        "week": -0.29,
        "volume_std": 290359235.6839187,
        "volume_mean": 239197044.22845218,
        "last_24hour_volume": 196262224.15529788,
        "upper_std": -0.15
    },
    "klay-token": {
        "symbol": "KLAY",
        "hour": 1.33,
        "day": 0.09,
        "week": 4.84,
        "volume_std": 63676084.52659947,
        "volume_mean": 66628784.70888049,
        "last_24hour_volume": 70773895.47893639,
        "upper_std": 0.07
    },
    "cdai": {
        "symbol": "CDAI",
        "hour": 0.6,
        "day": 0.02,
        "week": 0.19,
        "volume_std": 233457895.5354991,
        "volume_mean": 80251369.62003699,
        "last_24hour_volume": 17133316.30207843,
        "upper_std": -0.27
    },
    "the-graph": {
        "symbol": "GRT",
        "hour": 2.87,
        "day": 16.89,
        "week": 16.94,
        "volume_std": 105582026.13876374,
        "volume_mean": 180948217.76111245,
        "last_24hour_volume": 471841186.8387704,
        "upper_std": 2.76
    },
    "aave": {
        "symbol": "AAVE",
        "hour": 0.61,
        "day": -0.9,
        "week": -1.38,
        "volume_std": 136658018.48074615,
        "volume_mean": 336795175.3007024,
        "last_24hour_volume": 195255676.49411893,
        "upper_std": -1.04
    },
    "ecash": {
        "symbol": "XEC",
        "hour": 0.19,
        "day": -5.62,
        "week": -5.35,
        "volume_std": 229806469.53731748,
        "volume_mean": 139677418.98503506,
        "last_24hour_volume": 277855746.29307675,
        "upper_std": 0.6
    },
    "quant-network": {
        "symbol": "QNT",
        "hour": 0.75,
        "day": 0.36,
        "week": -5.63,
        "volume_std": 98357652.08343229,
        "volume_mean": 90078280.0082597,
        "last_24hour_volume": 57600073.7647546,
        "upper_std": -0.33
    },
    "compound-usd-coin": {
        "symbol": "CUSDC",
        "hour": 0.57,
        "day": -0.97,
        "week": 0.24,
        "volume_std": 167197503.03323427,
        "volume_mean": 60121017.12220713,
        "last_24hour_volume": 8823924.310974576,
        "upper_std": -0.31
    },
    "bitcoin-cash-abc-2": {
        "symbol": "BCHA",
        "hour": 2.86,
        "day": -0.37,
        "week": 0.34,
        "volume_std": 376648201.45838547,
        "volume_mean": 267383843.27830184,
        "last_24hour_volume": 30978.159545576607,
        "upper_std": -0.71
    },
    "iota": {
        "symbol": "MIOTA",
        "hour": 0.19,
        "day": -3.73,
        "week": -3.12,
        "volume_std": 154724202.3591522,
        "volume_mean": 137092504.7142678,
        "last_24hour_volume": 84683771.62644874,
        "upper_std": -0.34
    },
    "bitcoin-cash-sv": {
        "symbol": "BSV",
        "hour": 0.26,
        "day": -1.48,
        "week": -1.48,
        "volume_std": 107237487.21791399,
        "volume_mean": 331503116.8225684,
        "last_24hour_volume": 341584537.6174306,
        "upper_std": 0.09
    },
    "kusama": {
        "symbol": "KSM",
        "hour": 0.87,
        "day": 1.81,
        "week": 3.98,
        "volume_std": 138121460.88994983,
        "volume_mean": 223188226.77058566,
        "last_24hour_volume": 185845324.7383245,
        "upper_std": -0.27
    },
    "neo": {
        "symbol": "NEO",
        "hour": 0.49,
        "day": -0.69,
        "week": -3.54,
        "volume_std": 238727655.6894369,
        "volume_mean": 466965751.4245678,
        "last_24hour_volume": 287232497.2159331,
        "upper_std": -0.75
    },
    "waves": {
        "symbol": "WAVES",
        "hour": 0.34,
        "day": -7.95,
        "week": 11.1,
        "volume_std": 147684215.97605646,
        "volume_mean": 212856503.21749106,
        "last_24hour_volume": 177346427.2403737,
        "upper_std": -0.24
    },
    "olympus": {
        "symbol": "OHM",
        "hour": 1.35,
        "day": 0.73,
        "week": 26.04,
        "volume_std": 50470984.614903584,
        "volume_mean": 26716069.165937677,
        "last_24hour_volume": 449093488.6680095,
        "upper_std": 8.37
    },
    "arweave": {
        "symbol": "AR",
        "hour": -0.63,
        "day": 3.79,
        "week": -11.74,
        "volume_std": 95393741.98467797,
        "volume_mean": 87056159.02503587,
        "last_24hour_volume": 63843373.03014378,
        "upper_std": -0.24
    },
    "terrausd": {
        "symbol": "UST",
        "hour": 0.14,
        "day": -0.62,
        "week": 0.01,
        "volume_std": 42512919.24314231,
        "volume_mean": 78051700.22379282,
        "last_24hour_volume": 46609338.90308244,
        "upper_std": -0.74
    },
    "leo-token": {
        "symbol": "LEO",
        "hour": 0.23,
        "day": 6.86,
        "week": 2.12,
        "volume_std": 1154767.9564889187,
        "volume_mean": 2658390.078603856,
        "last_24hour_volume": 1637594.0252069838,
        "upper_std": -0.88
    },
    "huobi-btc": {
        "symbol": "HBTC",
        "hour": 2.43,
        "day": 4.54,
        "week": 14.84,
        "volume_std": 8761012.537839737,
        "volume_mean": 8898103.153775,
        "last_24hour_volume": 2263698.336421267,
        "upper_std": -0.76
    },
    "celsius-degree-token": {
        "symbol": "CEL",
        "hour": -0.1,
        "day": 1.87,
        "week": 2.21,
        "volume_std": 6354548.787708359,
        "volume_mean": 11125736.833551122,
        "last_24hour_volume": 10455465.086125653,
        "upper_std": -0.11
    },
    "amp-token": {
        "symbol": "AMP",
        "hour": 2.18,
        "day": 11.14,
        "week": 7.86,
        "volume_std": 41523866.150002025,
        "volume_mean": 46275250.24097074,
        "last_24hour_volume": 50018024.93650786,
        "upper_std": 0.09
    },
    "bittorrent-2": {
        "symbol": "BTT",
        "hour": 0.63,
        "day": -2.06,
        "week": -1.62,
        "volume_std": 296697315.2663346,
        "volume_mean": 478598591.52323055,
        "last_24hour_volume": 401571566.72420055,
        "upper_std": -0.26
    },
    "harmony": {
        "symbol": "ONE",
        "hour": -0.11,
        "day": 1.12,
        "week": -1.84,
        "volume_std": 153348713.3698483,
        "volume_mean": 144133683.85718605,
        "last_24hour_volume": 169502597.4128313,
        "upper_std": 0.17
    },
    "maker": {
        "symbol": "MKR",
        "hour": 0.72,
        "day": 0.91,
        "week": 3.94,
        "volume_std": 35203049.535281055,
        "volume_mean": 99212363.8549825,
        "last_24hour_volume": 78280943.23194218,
        "upper_std": -0.59
    },
    "sushi": {
        "symbol": "SUSHI",
        "hour": 0.57,
        "day": 1.49,
        "week": 2.66,
        "volume_std": 214942870.57909602,
        "volume_mean": 403870226.1187827,
        "last_24hour_volume": 305944365.01614803,
        "upper_std": -0.46
    },
    "thorchain": {
        "symbol": "RUNE",
        "hour": 1.69,
        "day": 0.69,
        "week": -2.85,
        "volume_std": 57755097.02611908,
        "volume_mean": 112790043.77246176,
        "last_24hour_volume": 54338741.09692799,
        "upper_std": -1.01
    },
    "blockstack": {
        "symbol": "STX",
        "hour": 0.82,
        "day": -7.95,
        "week": 39.27,
        "volume_std": 126739819.10809977,
        "volume_mean": 61661376.03839962,
        "last_24hour_volume": 62447295.40780521,
        "upper_std": 0.01
    },
    "helium": {
        "symbol": "HNT",
        "hour": -0.08,
        "day": 4.02,
        "week": 6.24,
        "volume_std": 20803277.484576806,
        "volume_mean": 25324606.91570665,
        "last_24hour_volume": 31094921.46385704,
        "upper_std": 0.28
    },
    "dash": {
        "symbol": "DASH",
        "hour": 0.26,
        "day": 2.79,
        "week": 2.85,
        "volume_std": 154528204.71236086,
        "volume_mean": 446756579.9820663,
        "last_24hour_volume": 408716913.96133626,
        "upper_std": -0.25
    },
    "omisego": {
        "symbol": "OMG",
        "hour": 0.5,
        "day": -2.64,
        "week": 0.7,
        "volume_std": 689356707.4331001,
        "volume_mean": 728834506.6877338,
        "last_24hour_volume": 769738248.2234914,
        "upper_std": 0.06
    },
    "compound-governance-token": {
        "symbol": "COMP",
        "hour": 1.13,
        "day": 2.15,
        "week": 1.82,
        "volume_std": 77424727.78752226,
        "volume_mean": 190131445.7900682,
        "last_24hour_volume": 148389826.86915675,
        "upper_std": -0.54
    },
    "celo": {
        "symbol": "CELO",
        "hour": 1.52,
        "day": 1.95,
        "week": 1.67,
        "volume_std": 199895756.17609248,
        "volume_mean": 136946894.3545545,
        "last_24hour_volume": 78374644.58996673,
        "upper_std": -0.29
    },
    "chiliz": {
        "symbol": "CHZ",
        "hour": 1.53,
        "day": 0.37,
        "week": -1.77,
        "volume_std": 195989657.13053054,
        "volume_mean": 322768214.7923474,
        "last_24hour_volume": 260821554.76485646,
        "upper_std": -0.32
    },
    "havven": {
        "symbol": "SNX",
        "hour": 1.02,
        "day": -3.13,
        "week": -1.26,
        "volume_std": 68750317.80513707,
        "volume_mean": 143133732.86281818,
        "last_24hour_volume": 90357196.50316922,
        "upper_std": -0.77
    },
    "magic-internet-money": {
        "symbol": "MIM",
        "hour": 0.29,
        "day": -0.42,
        "week": -0.05,
        "volume_std": 25104108.012253553,
        "volume_mean": 14747940.257336631,
        "last_24hour_volume": 81645434.91399843,
        "upper_std": 2.66
    },
    "ecomi": {
        "symbol": "OMI",
        "hour": 0.23,
        "day": 6.42,
        "week": 5.02,
        "volume_std": 4201187.195273815,
        "volume_mean": 7345299.259483788,
        "last_24hour_volume": 10825852.802283855,
        "upper_std": 0.83
    },
    "holotoken": {
        "symbol": "HOT",
        "hour": 0.3,
        "day": 0.16,
        "week": -1.37,
        "volume_std": 99761538.09556633,
        "volume_mean": 189559878.09772965,
        "last_24hour_volume": 185453911.51383767,
        "upper_std": -0.04
    },
    "decred": {
        "symbol": "DCR",
        "hour": 1.43,
        "day": -2.74,
        "week": -3.58,
        "volume_std": 7178495.246314893,
        "volume_mean": 18496283.03536475,
        "last_24hour_volume": 10917670.327652682,
        "upper_std": -1.06
    },
    "theta-fuel": {
        "symbol": "TFUEL",
        "hour": -0.28,
        "day": -3.37,
        "week": -7.3,
        "volume_std": 48300671.043914765,
        "volume_mean": 61111621.736353494,
        "last_24hour_volume": 46751044.576258264,
        "upper_std": -0.3
    },
    "nem": {
        "symbol": "XEM",
        "hour": 0.12,
        "day": -3.4,
        "week": -2.46,
        "volume_std": 56469219.73145045,
        "volume_mean": 99385825.55058317,
        "last_24hour_volume": 67477842.43129715,
        "upper_std": -0.57
    },
    "enjincoin": {
        "symbol": "ENJ",
        "hour": 0.89,
        "day": 1.43,
        "week": -3.79,
        "volume_std": 108195432.75332141,
        "volume_mean": 170710324.93343827,
        "last_24hour_volume": 116167643.8696278,
        "upper_std": -0.5
    },
    "zcash": {
        "symbol": "ZEC",
        "hour": 0.58,
        "day": 2.02,
        "week": 2.39,
        "volume_std": 174885205.152831,
        "volume_mean": 392799475.70734197,
        "last_24hour_volume": 290312053.03963995,
        "upper_std": -0.59
    },
    "xdce-crowd-sale": {
        "symbol": "XDC",
        "hour": -0.57,
        "day": -5.14,
        "week": -8.3,
        "volume_std": 5915505.7687740885,
        "volume_mean": 9945044.869310515,
        "last_24hour_volume": 10790553.387260504,
        "upper_std": 0.14
    },
    "icon": {
        "symbol": "ICX",
        "hour": 1.45,
        "day": -2.26,
        "week": -4.16,
        "volume_std": 67727962.6626432,
        "volume_mean": 91627041.2261663,
        "last_24hour_volume": 43991255.60607137,
        "upper_std": -0.7
    },
    "qtum": {
        "symbol": "QTUM",
        "hour": 1.11,
        "day": -3.29,
        "week": 2.0,
        "volume_std": 235947791.47074986,
        "volume_mean": 367557200.9706245,
        "last_24hour_volume": 266395751.10988024,
        "upper_std": -0.43
    },
    "dydx": {
        "symbol": "DYDX",
        "hour": 0.86,
        "day": -2.04,
        "week": 5.43,
        "volume_std": 284742472.4905729,
        "volume_mean": 548366308.9621098,
        "last_24hour_volume": 314538118.37199306,
        "upper_std": -0.82
    },
    "true-usd": {
        "symbol": "TUSD",
        "hour": 0.11,
        "day": -0.13,
        "week": -0.14,
        "volume_std": 80035488.2445801,
        "volume_mean": 89200617.73655124,
        "last_24hour_volume": 107773845.80423722,
        "upper_std": 0.23
    },
    "yearn-finance": {
        "symbol": "YFI",
        "hour": 0.85,
        "day": 0.65,
        "week": 4.19,
        "volume_std": 72192232.10949123,
        "volume_mean": 233088882.68826357,
        "last_24hour_volume": 218320335.2857321,
        "upper_std": -0.2
    },
    "telcoin": {
        "symbol": "TEL",
        "hour": 1.08,
        "day": -4.86,
        "week": 23.95,
        "volume_std": 11013064.758827481,
        "volume_mean": 18927899.35368412,
        "last_24hour_volume": 22149392.914404303,
        "upper_std": 0.29
    },
    "bitcoin-gold": {
        "symbol": "BTG",
        "hour": 1.53,
        "day": -5.03,
        "week": 6.23,
        "volume_std": 64636041.98144446,
        "volume_mean": 64976259.10526711,
        "last_24hour_volume": 34386687.741663344,
        "upper_std": -0.47
    },
    "zilliqa": {
        "symbol": "ZIL",
        "hour": 0.66,
        "day": -0.85,
        "week": -3.54,
        "volume_std": 50850290.087994836,
        "volume_mean": 118135286.26866627,
        "last_24hour_volume": 114997716.59022348,
        "upper_std": -0.06
    },
    "huobi-token": {
        "symbol": "HT",
        "hour": 0.91,
        "day": -0.0,
        "week": -2.71,
        "volume_std": 232617455.6740156,
        "volume_mean": 267596060.38094208,
        "last_24hour_volume": 70420116.99465673,
        "upper_std": -0.85
    },
    "iostoken": {
        "symbol": "IOST",
        "hour": 0.77,
        "day": -3.33,
        "week": -6.55,
        "volume_std": 436483363.5410781,
        "volume_mean": 333329960.71580446,
        "last_24hour_volume": 206105840.54294625,
        "upper_std": -0.29
    },
    "flow": {
        "symbol": "FLOW",
        "hour": 0.34,
        "day": -5.79,
        "week": -7.33,
        "volume_std": 251541792.17409304,
        "volume_mean": 167588988.17922285,
        "last_24hour_volume": 46299919.90715298,
        "upper_std": -0.48
    },
    "curve-dao-token": {
        "symbol": "CRV",
        "hour": 1.2,
        "day": 1.4,
        "week": 0.81,
        "volume_std": 129682340.32576226,
        "volume_mean": 216727786.73942426,
        "last_24hour_volume": 196870285.12573013,
        "upper_std": -0.15
    },
    "mina-protocol": {
        "symbol": "MINA",
        "hour": 0.71,
        "day": -1.36,
        "week": -5.29,
        "volume_std": 70256129.22235174,
        "volume_mean": 69350238.07271197,
        "last_24hour_volume": 38565340.24164375,
        "upper_std": -0.44
    },
    "ravencoin": {
        "symbol": "RVN",
        "hour": 0.92,
        "day": 1.34,
        "week": -1.99,
        "volume_std": 111687143.24407198,
        "volume_mean": 103423528.21388139,
        "last_24hour_volume": 66366233.42940866,
        "upper_std": -0.33
    },
    "time": "Oct 16 2021 03:14:59"
}